apt_inst.cpython-311-x86_64-linux-gnu.so
apt_pkg.cpython-311-x86_64-linux-gnu.so
apt/__init__.py
apt/auth.py
apt/cache.py
apt/cdrom.py
apt/debfile.py
apt/package.py
apt/py.typed
apt/utils.py
apt/progress/__init__.py
apt/progress/base.py
apt/progress/text.py
aptsources/__init__.py
aptsources/_deb822.py
aptsources/distinfo.py
aptsources/distro.py
aptsources/sourceslist.py
python_apt_binary-2.6.0.data/data/share/python-apt/templates/Blankon.mirrors
python_apt_binary-2.6.0.data/data/share/python-apt/templates/Debian.mirrors
python_apt_binary-2.6.0.data/data/share/python-apt/templates/Kali.mirrors
python_apt_binary-2.6.0.data/data/share/python-apt/templates/Tanglu.mirrors
python_apt_binary-2.6.0.data/data/share/python-apt/templates/Ubuntu.mirrors
python_apt_binary-2.6.0.data/data/share/python-apt/templates/gNewSense.mirrors
python_apt_binary-2.6.0.data/purelib/apt_inst-stubs/__init__.pyi
python_apt_binary-2.6.0.data/purelib/apt_pkg-stubs/__init__.pyi
python_apt_binary-2.6.0.dist-info/AUTHORS
python_apt_binary-2.6.0.dist-info/COPYING.GPL
python_apt_binary-2.6.0.dist-info/METADATA
python_apt_binary-2.6.0.dist-info/WHEEL
python_apt_binary-2.6.0.dist-info/top_level.txt
python_apt_binary-2.6.0.dist-info/RECORD
