Metadata-Version: 2.1
Name: python-apt-binary
Version: 2.6.0
Summary: Python bindings for APT
Author: APT Development Team
Author-email: deity@lists.debian.org
License: GNU GPL
Platform: posix
License-File: COPYING.GPL
License-File: AUTHORS
